pbshm_framework-0.7.1.dist-info/licenses/LICENSE
rosehips/__init__.py
rosehips/layout/__init__.py
rosehips/layout/layout.py
rosehips/layout/static/logo.png
rosehips/layout/static/logo_minimum.png
rosehips/layout/static/style.css
rosehips/layout/templates/base.html
rosehips/layout/templates/home.html
rosehips/layout/templates/portal.html
rosehips/sideloader/__init__.py
rosehips/sideloader/sideloader.py
rosehips/sideloader/static/sideload.json
rosehips/sideloader/templates/sideload-modules.html
pbshm_framework-0.7.1.dist-info/METADATA
pbshm_framework-0.7.1.dist-info/WHEEL
pbshm_framework-0.7.1.dist-info/top_level.txt
pbshm_framework-0.7.1.dist-info/RECORD
