Metadata-Version: 2.4
Name: pbshm-framework
Version: 0.7.1
Summary: PBSHM Framework
Author-email: Dan Brennan <d.s.brennan@sheffield.ac.uk>
License:                     GNU AFFERO GENERAL PUBLIC LICENSE
Project-URL: homepage, https://github.com/dynamics-research-group/pbshm-framework
Classifier: License :: OSI Approved :: GNU Affero General Public License v3 or later (AGPLv3+)
Classifier: Programming Language :: Python :: 3
Classifier: Framework :: Flask
Requires-Python: >=3.11
License-File: LICENSE
Requires-Dist: pbshm-core==1.1.6
Requires-Dist: pbshm-channel-toolbox==0.1.4
Requires-Dist: pbshm-ie-toolbox==0.1.4
Requires-Dist: pbshm-network-mcs==0.1.1
Requires-Dist: pbshm-ie-visualiser==1.0
Dynamic: license-file
